{
  "Rows": {
    "RowColumnAttachedInfos": {
      "3": {
        "GridRowColumnDefinition": {
          "DesignLengthInPixel": 16.0
        }
      },
      "6": {
        "GridRowColumnDefinition": {
          "DesignLengthInPixel": 15.0
        }
      },
      "7": {
        "GridRowColumnDefinition": {
          "DesignLengthInPixel": 30.0
        }
      },
      "8": {
        "GridRowColumnDefinition": {
          "DesignLengthInPixel": 19.0
        }
      },
      "9": {
        "GridRowColumnDefinition": {
          "DesignLengthInPixel": 30.0
        }
      },
      "10": {
        "GridRowColumnDefinition": {
          "DesignLengthInPixel": 15.0
        }
      },
      "11": {
        "GridRowColumnDefinition": {
          "DesignLengthInPixel": 30.0
        }
      },
      "12": {
        "GridRowColumnDefinition": {
          "DesignLengthInPixel": 15.0
        }
      },
      "13": {
        "GridRowColumnDefinition": {
          "DesignLengthInPixel": 30.0
        }
      },
      "14": {
        "GridRowColumnDefinition": {
          "DesignLengthInPixel": 15.0
        }
      },
      "15": {
        "GridRowColumnDefinition": {
          "DesignLengthInPixel": 30.0
        }
      },
      "16": {
        "GridRowColumnDefinition": {
          "DesignLengthInPixel": 15.0
        }
      },
      "17": {
        "GridRowColumnDefinition": {
          "DesignLengthInPixel": 30.0
        }
      },
      "18": {
        "GridRowColumnDefinition": {
          "DesignLengthInPixel": 26.0
        }
      },
      "21": {
        "GridRowColumnDefinition": {
          "DesignLengthInPixel": 20.0
        }
      },
      "4": {
        "GridRowColumnDefinition": {
          "DesignLengthInPixel": 16.0
        }
      },
      "20": {
        "GridRowColumnDefinition": {
          "DesignLengthInPixel": 29.0
        }
      }
    },
    "InLogicalVisibleIndexes": [
      5
    ],
    "Count": 22
  },
  "Cols": {
    "RowColumnAttachedInfos": {
      "5": {
        "GridRowColumnDefinition": {
          "DesignLengthInPixel": 5.0
        }
      },
      "6": {
        "GridRowColumnDefinition": {
          "DesignLengthInPixel": 5.0
        }
      },
      "7": {
        "GridRowColumnDefinition": {
          "DesignLengthInPixel": 10.0
        }
      },
      "8": {
        "GridRowColumnDefinition": {
          "DesignLengthInPixel": 5.0
        }
      },
      "9": {
        "GridRowColumnDefinition": {
          "DesignLengthInPixel": 5.0
        }
      },
      "10": {
        "GridRowColumnDefinition": {
          "DesignLengthInPixel": 10.0
        }
      }
    },
    "Count": 39
  },
  "Values": {
    "1,1": "품목 등록",
    "5,2": "ID:",
    "7,2": "품목코드:",
    "9,2": "제품명:",
    "11,2": "규격:",
    "13,2": "품목구분:",
    "15,2": "단가",
    "17,2": "파일관리:",
    "20,1": "저장",
    "20,6": "닫기"
  },
  "AttachInfos": {
    "5,12": {
      "BindingInfo": {
        "TableName": "제품",
        "ColumnName": "ID"
      }
    },
    "7,12": {
      "CellType": {
        "$type": "Forguncy.TextCellType, ServerDesignerCommon",
        "SavedValidators": [
          {
            "$type": "Forguncy.CellTypes.Models.UniqueValidadator, ServerDesignerCommon",
            "Enabled": true
          }
        ],
        "TemplateKey": "_RS_LightLine_Translucent_SmallRoundCorner_Normal1"
      },
      "BindingInfo": {
        "TableName": "제품",
        "ColumnName": "품목코드"
      },
      "DataValidationInfo": {
        "IgnoreBlank": false
      }
    },
    "9,12": {
      "CellType": {
        "$type": "Forguncy.TextCellType, ServerDesignerCommon",
        "SavedValidators": [
          {
            "$type": "Forguncy.CellTypes.Models.UniqueValidadator, ServerDesignerCommon"
          }
        ],
        "TemplateKey": "_RS_LightLine_Translucent_SmallRoundCorner_Normal1"
      },
      "BindingInfo": {
        "TableName": "제품",
        "ColumnName": "제품명"
      },
      "DataValidationInfo": {
        "IgnoreBlank": false
      }
    },
    "11,12": {
      "CellType": {
        "$type": "Forguncy.TextCellType, ServerDesignerCommon",
        "SavedValidators": [
          {
            "$type": "Forguncy.CellTypes.Models.UniqueValidadator, ServerDesignerCommon"
          }
        ],
        "TemplateKey": "_RS_LightLine_Translucent_SmallRoundCorner_Normal1"
      },
      "BindingInfo": {
        "TableName": "제품",
        "ColumnName": "규격명"
      }
    },
    "13,12": {
      "CellType": {
        "$type": "Forguncy.RadioGroupCellType, ServerDesignerCommon",
        "NoneItemText": "<없음>",
        "Style": 1,
        "Items": [
          {
            "Value": "원재료",
            "DisplayValue": "원재료"
          },
          {
            "Value": "부재료",
            "DisplayValue": "부재료"
          },
          {
            "Value": "제품",
            "DisplayValue": "제품"
          },
          {
            "Value": "반제품",
            "DisplayValue": "반제품"
          },
          {
            "Value": "상품",
            "DisplayValue": "상품"
          },
          {
            "Value": "무형상품",
            "DisplayValue": "무형상품"
          }
        ]
      },
      "BindingInfo": {
        "TableName": "제품",
        "ColumnName": "품목구분"
      }
    },
    "15,12": {
      "CellType": {
        "$type": "Forguncy.NumberCellType, ServerDesignerCommon",
        "TemplateKey": "_RS_LightLine_Translucent_SmallRoundCorner_Normal1"
      },
      "BindingInfo": {
        "TableName": "제품",
        "ColumnName": "가격"
      },
      "DataValidationInfo": {
        "IgnoreBlank": false
      }
    },
    "17,12": {
      "CellType": {
        "$type": "Forguncy.AttachmentCelltype, ServerDesignerCommon",
        "UploadLimit": {
          "ExtensionFilter": ".jpg, .jpeg, .png, .gif, .bmp, .xlsx, .docx, .doc, .xls, .pdf",
          "ReplaceWhenOneFile": true
        },
        "TemplateKey": "_RS_Normal_Style2"
      },
      "BindingInfo": {
        "TableName": "제품",
        "ColumnName": "파일관리"
      }
    },
    "20,1": {
      "CellType": {
        "$type": "Forguncy.ButtonCellType, ServerDesignerCommon",
        "CommandList": [
          {
            "$type": "Forguncy.Model.ConditionCommand, ServerDesignerCommon",
            "ConditionAndCommandPairList": [
              {
                "Condition": {
                  "$type": "Forguncy.Model.IfCondition, ServerDesignerCommon",
                  "param": {
                    "$type": "Forguncy.Model.IfConditionPageElementParam, ServerDesignerCommon",
                    "cellLocations": [
                      {
                        "SerializeProperty": "='제품 등록 페이지'!B21"
                      }
                    ]
                  },
                  "value": "저장",
                  "Id": "7d17591b-6696-41a5-8e27-be513c9036f7"
                },
                "CommandList": [
                  {
                    "$type": "Forguncy.Model.UpdateDataTableCommand, ServerDesignerCommon",
                    "TableName": "제품",
                    "UpdateType": "add",
                    "ConfirmText": "데이터를 추가하시겠습니까?",
                    "UpdateValues": []
                  }
                ],
                "ID": "14734d68-342f-4bfa-88ff-c7141fd75160"
              },
              {
                "Condition": {
                  "$type": "Forguncy.Model.IfCondition, ServerDesignerCommon",
                  "param": {
                    "$type": "Forguncy.Model.IfConditionPageElementParam, ServerDesignerCommon",
                    "cellLocations": [
                      {
                        "SerializeProperty": "='제품 등록 페이지'!B21"
                      }
                    ]
                  },
                  "value": "수정",
                  "Id": "38a286f8-32ae-4f42-8c85-97cd422138ba"
                },
                "CommandList": [
                  {
                    "$type": "Forguncy.Model.UpdateDataTableCommand, ServerDesignerCommon",
                    "TableName": "제품",
                    "ConfirmText": "데이터를 업데이트하시겠습니까?",
                    "UpdateValues": []
                  }
                ],
                "ID": "9895292b-09d4-4639-9db9-ddb6c8e44719"
              }
            ]
          },
          {
            "$type": "Forguncy.Model.ClosePopupCommand, ServerDesignerCommon",
            "PassValueBack": true,
            "ReloadData": true,
            "PassQueryCondition": true
          }
        ],
        "Text": "저장",
        "TemplateKey": "스타일4"
      }
    },
    "20,6": {
      "CellType": {
        "$type": "Forguncy.ButtonCellType, ServerDesignerCommon",
        "CommandList": [
          {
            "$type": "Forguncy.Model.NavigateCommand, ServerDesignerCommon",
            "PageName": "제품_목록 페이지",
            "PassValues": []
          }
        ],
        "Text": "닫기",
        "TemplateKey": "스타일5"
      }
    }
  },
  "StyleDatas": {
    "Styles": [
      {
        "FontFamily": 0,
        "FontSize": 18.666666666666664,
        "FontWeight": 1,
        "Formatter": 2
      },
      {
        "FontFamily": 0
      },
      {
        "FontSize": 18.666666666666664,
        "FontWeight": 1,
        "HorizontalAlignment": 3
      },
      {
        "FontSize": 18.666666666666664,
        "FontWeight": 1
      },
      {
        "Background": null
      },
      {
        "FontWeight": 1
      },
      {
        "Background": 4,
        "Formatter": 5
      },
      {
        "FontWeight": 1,
        "Formatter": 2
      },
      {
        "Background": 4,
        "HorizontalAlignment": 6
      },
      {
        "Underline": true
      },
      {
        "Background": 7
      },
      {
        "Background": 8
      }
    ],
    "Types": {
      "Strs": [
        "나눔스퀘어",
        "Bold",
        "[AUTO]General",
        "Center",
        "Background 1 0",
        "@",
        "Left",
        "#FFF2F2F2",
        "Background 1 -5"
      ]
    },
    "CellStyles": {
      "1,1": 0,
      "1,2": 1,
      "1,3": 1,
      "1,4": 1,
      "1,5": 1,
      "1,8": 1,
      "1,9": 0,
      "1,11": 2,
      "1,12": 2,
      "1,13": 2,
      "1,14": 2,
      "1,15": 2,
      "1,16": 2,
      "1,17": 2,
      "1,18": 2,
      "1,19": 2,
      "1,20": 2,
      "1,21": 2,
      "1,22": 2,
      "1,23": 2,
      "1,24": 2,
      "1,25": 2,
      "1,26": 2,
      "1,27": 2,
      "1,28": 2,
      "1,29": 2,
      "1,30": 2,
      "1,31": 2,
      "1,32": 2,
      "1,33": 2,
      "1,34": 2,
      "1,35": 2,
      "1,36": 2,
      "1,37": 2,
      "1,38": 2,
      "2,1": 1,
      "2,2": 1,
      "2,3": 1,
      "2,4": 1,
      "2,5": 1,
      "2,8": 1,
      "2,9": 0,
      "3,1": 3,
      "3,2": 3,
      "3,3": 3,
      "3,4": 3,
      "3,5": 3,
      "3,6": 3,
      "3,7": 3,
      "4,0": 4,
      "4,1": 3,
      "4,2": 3,
      "4,3": 3,
      "4,4": 3,
      "4,5": 3,
      "4,6": 3,
      "4,7": 3,
      "4,38": 4,
      "5,0": 4,
      "5,2": 5,
      "5,38": 4,
      "6,0": 4,
      "6,38": 4,
      "7,0": 4,
      "7,2": 5,
      "7,12": 6,
      "7,38": 4,
      "8,0": 4,
      "8,38": 4,
      "9,0": 4,
      "9,2": 5,
      "9,12": 6,
      "9,38": 4,
      "10,0": 4,
      "10,38": 4,
      "11,0": 4,
      "11,2": 7,
      "11,12": 6,
      "11,38": 4,
      "12,0": 4,
      "12,38": 4,
      "13,0": 4,
      "13,2": 5,
      "13,38": 4,
      "14,0": 4,
      "14,38": 4,
      "15,0": 4,
      "15,2": 7,
      "15,12": 8,
      "15,38": 4,
      "16,0": 4,
      "16,38": 4,
      "17,0": 4,
      "17,2": 5,
      "17,12": 9,
      "17,38": 4,
      "18,0": 4,
      "18,38": 4,
      "20,1": 1,
      "20,2": 1,
      "20,3": 1,
      "20,4": 1,
      "20,5": 1,
      "20,6": 1
    },
    "RowStyles": {
      "4": 10,
      "5": 11,
      "6": 11,
      "7": 11,
      "8": 11,
      "9": 11,
      "10": 11,
      "11": 11,
      "12": 11,
      "13": 11,
      "14": 11,
      "15": 11,
      "16": 11,
      "17": 11,
      "18": 11
    },
    "ColStyles": {
      "0": 4,
      "38": 4
    },
    "SheetStyle": {
      "FontFamily": 0
    }
  },
  "Spans": [
    "5,12,1,6",
    "7,12,1,25",
    "9,12,1,25",
    "11,12,1,25",
    "13,12,1,25",
    "15,12,1,25",
    "17,12,1,25",
    "1,1,2,9",
    "20,1,1,4",
    "20,6,1,6"
  ],
  "PageInfo": {
    "$type": "Forguncy.Model.Pages.NormalPage, ServerDesignerCommon",
    "ShouldCheckDirty": true,
    "AuthorizeInfo": {
      "VisitMode": 2
    },
    "RowBreakLines": [],
    "RepeatRangeSettings": []
  },
  "PrintInfo": {
    "Margin": {},
    "PaperSize": {}
  }
}//0bVeJ1TNeXa2KStGVlusXLdZuXgounv/unlIRtvjQwi0vawfjeBYWasNonLB+fQ4X6W4/Xj+3DQVaq7strpY6mW7BrHlBXQYSAdnfqQSEl8qW/Tx67m2qpeuNQYc8Wk0C3PVKzv8TK+IwKxn/Nxj5FEStYVQUT1qqNcdK7mh/HUL+dUY9UkRK4In7up3XwRHMXjb0V+HIui/UT6rAWGrFSLUZoVqqeYfdg60IL492glK3DM0NL16lz11b86D2hafMnPtWk1kn3Sf5SusiMeJoWYNVeg5Cutwr+PnjRLqiWwjt3T7DjUSu7kXMKMZKrpNYgpOM4MyzNJBZuLInq3FHdpr+oyEN0rs8WcM0hYXlotkG/QDCn+m8OktjYNeguO52dCw679C9uwbyZYyrp3f0BWKJ3ARgaqUid8s4HPRM6jsVw2OTn+z7tzKsXY8e52eRjqynlnS5rfhxJ4DdX7V5B8jv4OKHCClrVKBomj0TsSX4ad4edFj9QpMbKG29kwAGdPq3ePjXNL673PEekTp0WrJluijtP0BVfMKNx25xMlONgSkEN4d/tpMbOA/buQ9cFDth+JOb2UoINXkQRmD2NYkVOEGf7xbOg00H+xaeegWlXjfCi8dqR8THoTf9E3QTFWaG6ZMPc3jtj69Me1Wh6e7SYBIc2EgcjEhzjdG3un0IBIM2DR5wmqYiZN1WxcE7DJ1XRvDddMOEdTEcLpl1XyIV05hSPnRhYMZm0WO9/EKqrc/vTBXC0zYQTBSRpq+9t9Osa69sEz+8nskliaCmG2pnaZME5G0tq4AwWYK1AEE7ovOpV4OvrSZq5z9lQHQdMs0ej5GisYRLaRTRDSfRgNNBq6wJ4g6/qFWtJBccSoaFNuUGDrHvzXtU8ytvN0noBcimkGRb7EFgtq1Z7NpMQ==|920